h3_syllable/__init__.py
h3_syllable/cli.py
h3_syllable/config_loader.py
h3_syllable/h3_syllable_system.py
h3_syllable/utilities.py
h3_syllable/validation.py
h3_syllable/configs/ascii-dnqqwn.json
h3_syllable/configs/config_index.py
hex_address-1.3.1.dist-info/METADATA
hex_address-1.3.1.dist-info/WHEEL
hex_address-1.3.1.dist-info/entry_points.txt
hex_address-1.3.1.dist-info/top_level.txt
hex_address-1.3.1.dist-info/RECORD
