Metadata-Version: 2.4
Name: hex-address
Version: 1.3.1
Summary: Convert GPS coordinates to memorable hex addresses using H3
Author-email: Álvaro Silva <alvaro@sanluca.cc>
License: MIT
Project-URL: Homepage, https://hex-address-app.vercel.app/
Project-URL: Documentation, https://hex-address-app.vercel.app/
Project-URL: Repository, https://github.com/alvasilvao/hex-address.git
Project-URL: Bug Tracker, https://github.com/alvasilvao/hex-address/issues
Keywords: h3,gps,coordinates,hex,address,geospatial,mapping
Classifier: Development Status :: 5 - Production/Stable
Classifier: Intended Audience :: Developers
Classifier: License :: OSI Approved :: MIT License
Classifier: Programming Language :: Python :: 3
Classifier: Programming Language :: Python :: 3.8
Classifier: Programming Language :: Python :: 3.9
Classifier: Programming Language :: Python :: 3.10
Classifier: Programming Language :: Python :: 3.11
Classifier: Programming Language :: Python :: 3.12
Classifier: Topic :: Scientific/Engineering :: GIS
Classifier: Topic :: Software Development :: Libraries :: Python Modules
Classifier: Topic :: Utilities
Requires-Python: >=3.8
Requires-Dist: h3<5.0.0,>=4.0.0
Provides-Extra: dev
Requires-Dist: pytest>=7.0.0; extra == "dev"
Requires-Dist: pytest-cov>=4.0.0; extra == "dev"
Requires-Dist: black>=23.0.0; extra == "dev"
Requires-Dist: ruff>=0.1.0; extra == "dev"
Requires-Dist: mypy>=1.0.0; extra == "dev"
Requires-Dist: build>=0.10.0; extra == "dev"
Requires-Dist: twine>=4.0.0; extra == "dev"
Provides-Extra: test
Requires-Dist: pytest>=7.0.0; extra == "test"
Requires-Dist: pytest-cov>=4.0.0; extra == "test"
